{
	"class" : {
		 },
	"instance" : {
		"commitsDo:" : " 11/28/2016 11:42:15",
		"firstCommit" : " 11/28/2016 11:42:15",
		"fromBranch:" : " 11/28/2016 11:42:15",
		"fromCommit:" : " 11/28/2016 11:42:15",
		"fromCommitId:" : " 11/28/2016 11:42:15",
		"fromHead" : " 11/28/2016 11:42:15",
		"fromLGitId:" : " 11/28/2016 11:42:15",
		"fromTag:" : " 11/28/2016 11:42:15",
		"rawResultsDo:" : " 11/28/2016 11:42:15",
		"revwalk" : " 11/28/2016 11:42:15",
		"shouldInclude:" : " 11/28/2016 11:42:15",
		"uptoCommit:" : " 11/28/2016 11:42:15" } }
